qm_tools_aw/__init__.py
qm_tools_aw/molecular_visualization.py
qm_tools_aw/periodictable.py
qm_tools_aw/plot.py
qm_tools_aw/qca.py
qm_tools_aw/sapt.py
qm_tools_aw/software_access.py
qm_tools_aw/tools.py
qm_tools_aw-1.5.3.dist-info/licenses/LICENSE
qm_tools_aw-1.5.3.dist-info/METADATA
qm_tools_aw-1.5.3.dist-info/WHEEL
qm_tools_aw-1.5.3.dist-info/top_level.txt
qm_tools_aw-1.5.3.dist-info/RECORD
